omniglot/__init__.py
omniglot/__main__.py
omniglot/cli.py
omniglot-0.1.0.dist-info/DESCRIPTION.rst
omniglot-0.1.0.dist-info/METADATA
omniglot-0.1.0.dist-info/RECORD
omniglot-0.1.0.dist-info/WHEEL
omniglot-0.1.0.dist-info/entry_points.txt
omniglot-0.1.0.dist-info/metadata.json
omniglot-0.1.0.dist-info/top_level.txt
